[
  { "sign": "hello", "text": "Hello", "category": "general", "confidence": 0.98, "animation_id": "anim_hello" },
  { "sign": "yes", "text": "Yes", "category": "general", "confidence": 0.95, "animation_id": "anim_yes" },
  { "sign": "no", "text": "No", "category": "general", "confidence": 0.96, "animation_id": "anim_no" },
  { "sign": "thank you", "text": "Thank you", "category": "general", "confidence": 0.97, "animation_id": "anim_thank_you" },
  { "sign": "help", "text": "Help", "category": "emergency", "confidence": 0.99, "animation_id": "anim_help" },
  { "sign": "emergency", "text": "Emergency", "category": "emergency", "confidence": 0.99, "animation_id": "anim_emergency" },
  { "sign": "doctor", "text": "Doctor", "category": "medical", "confidence": 0.94, "animation_id": "anim_doctor" },
  { "sign": "pain", "text": "Pain", "category": "medical", "confidence": 0.92, "animation_id": "anim_pain" },
  { "sign": "medicine", "text": "Medicine", "category": "medical", "confidence": 0.93, "animation_id": "anim_medicine" },
  { "sign": "water", "text": "Water", "category": "request", "confidence": 0.96, "animation_id": "anim_water" },
  { "sign": "food", "text": "Food", "category": "request", "confidence": 0.95, "animation_id": "anim_food" },
  { "sign": "stop", "text": "Stop", "category": "general", "confidence": 0.97, "animation_id": "anim_stop" },
  { "sign": "okay", "text": "Okay", "category": "general", "confidence": 0.98, "animation_id": "anim_okay" },
  { "sign": "sorry", "text": "Sorry", "category": "general", "confidence": 0.94, "animation_id": "anim_sorry" },
  { "sign": "please repeat", "text": "Please repeat", "category": "request", "confidence": 0.91, "animation_id": "anim_please_repeat" },
  { "sign": "call family", "text": "Call family", "category": "request", "confidence": 0.92, "animation_id": "anim_call_family" },
  { "sign": "ambulance", "text": "Ambulance", "category": "emergency", "confidence": 0.99, "animation_id": "anim_ambulance" },
  { "sign": "accident", "text": "Accident", "category": "emergency", "confidence": 0.98, "animation_id": "anim_accident" },
  { "sign": "breathing problem", "text": "Breathing problem", "category": "emergency", "confidence": 0.99, "animation_id": "anim_breathing_problem" },
  { "sign": "fever", "text": "Fever", "category": "medical", "confidence": 0.94, "animation_id": "anim_fever" },
  { "sign": "dizzy", "text": "Dizzy", "category": "medical", "confidence": 0.91, "animation_id": "anim_dizzy" },
  { "sign": "bathroom", "text": "Bathroom", "category": "request", "confidence": 0.95, "animation_id": "anim_bathroom" },
  { "sign": "hungry", "text": "Hungry", "category": "request", "confidence": 0.96, "animation_id": "anim_hungry" },
  { "sign": "tired", "text": "Tired", "category": "general", "confidence": 0.93, "animation_id": "anim_tired" },
  { "sign": "scared", "text": "Scared", "category": "general", "confidence": 0.92, "animation_id": "anim_scared" },
  { "sign": "need help", "text": "Need help", "category": "emergency", "confidence": 0.99, "animation_id": "anim_need_help" },
  { "sign": "I am okay", "text": "I am okay", "category": "general", "confidence": 0.96, "animation_id": "anim_i_am_okay" },
  { "sign": "hospital", "text": "Hospital", "category": "medical", "confidence": 0.95, "animation_id": "anim_hospital" },
  { "sign": "danger", "text": "Danger", "category": "emergency", "confidence": 0.99, "animation_id": "anim_danger" },
  { "sign": "wait", "text": "Wait", "category": "general", "confidence": 0.94, "animation_id": "anim_wait" }
]
